insta_private_lib_api/__init__.py
insta_private_lib_api/config.py
insta_private_lib_api/exceptions.py
insta_private_lib_api/extractors.py
insta_private_lib_api/story.py
insta_private_lib_api/types.py
insta_private_lib_api/utils.py
insta_private_lib_api/zones.py
insta_private_lib_api/mixins/__init__.py
insta_private_lib_api/mixins/account.py
insta_private_lib_api/mixins/album.py
insta_private_lib_api/mixins/auth.py
insta_private_lib_api/mixins/bloks.py
insta_private_lib_api/mixins/challenge.py
insta_private_lib_api/mixins/clip.py
insta_private_lib_api/mixins/collection.py
insta_private_lib_api/mixins/comment.py
insta_private_lib_api/mixins/direct.py
insta_private_lib_api/mixins/explore.py
insta_private_lib_api/mixins/fbsearch.py
insta_private_lib_api/mixins/fundraiser.py
insta_private_lib_api/mixins/hashtag.py
insta_private_lib_api/mixins/highlight.py
insta_private_lib_api/mixins/igtv.py
insta_private_lib_api/mixins/insights.py
insta_private_lib_api/mixins/location.py
insta_private_lib_api/mixins/media.py
insta_private_lib_api/mixins/multiple_accounts.py
insta_private_lib_api/mixins/note.py
insta_private_lib_api/mixins/notification.py
insta_private_lib_api/mixins/password.py
insta_private_lib_api/mixins/photo.py
insta_private_lib_api/mixins/private.py
insta_private_lib_api/mixins/public.py
insta_private_lib_api/mixins/share.py
insta_private_lib_api/mixins/story.py
insta_private_lib_api/mixins/timeline.py
insta_private_lib_api/mixins/totp.py
insta_private_lib_api/mixins/track.py
insta_private_lib_api/mixins/user.py
insta_private_lib_api/mixins/video.py
test_proj_api_insta_ewqeqwadsd123-2.0.4.dist-info/LICENSE
test_proj_api_insta_ewqeqwadsd123-2.0.4.dist-info/METADATA
test_proj_api_insta_ewqeqwadsd123-2.0.4.dist-info/WHEEL
test_proj_api_insta_ewqeqwadsd123-2.0.4.dist-info/top_level.txt
test_proj_api_insta_ewqeqwadsd123-2.0.4.dist-info/RECORD
