Metadata-Version: 2.1
Name: test-proj-api-insta-ewqeqwadsd123
Version: 2.0.4
Summary: Fast and effective Instagram Private API wrapper
Home-page: https://github.com/savarety/insta_private_lib_api
Author: Nick Jaraf
Author-email: 
License: MIT
Keywords: instagram private api,instagram-private-api,instagram api,instagram-api,instagram,instagram-scraper,instagram-client,instagram-stories,instagram-feed,instagram-reels,instagram-insights,downloader,uploader,videos,photos,albums,igtv,reels,stories,pictures,instagram-user-photos,instagram-photos,instagram-metadata,instagram-downloader,instagram-uploader,instagram-note
Platform: UNKNOWN
Classifier: Development Status :: 4 - Beta
Classifier: Intended Audience :: Developers
Classifier: License :: OSI Approved :: MIT License
Classifier: Topic :: Software Development :: Libraries :: Python Modules
Classifier: Programming Language :: Python :: 3.8
Classifier: Programming Language :: Python :: 3.9
Requires-Python: >=3.8
License-File: LICENSE
Requires-Dist: requests (<3.0,>=2.25.1)
Requires-Dist: PySocks (==1.7.1)
Requires-Dist: pydantic (==1.10.9)
Requires-Dist: pycryptodomex (==3.18.0)
